crea/__init__.py
crea/account.py
crea/aes.py
crea/amount.py
crea/asciichart.py
crea/asset.py
crea/block.py
crea/blockchain.py
crea/blockchainobject.py
crea/cli.py
crea/comment.py
crea/constants.py
crea/conveyor.py
crea/crea.py
crea/creaconnect.py
crea/discussions.py
crea/exceptions.py
crea/imageuploader.py
crea/instance.py
crea/market.py
crea/memo.py
crea/message.py
crea/nodelist.py
crea/notify.py
crea/price.py
crea/profile.py
crea/rc.py
crea/snapshot.py
crea/storage.py
crea/transactionbuilder.py
crea/utils.py
crea/version.py
crea/vote.py
crea/wallet.py
crea/witness.py
creaapi/__init__.py
creaapi/creanoderpc.py
creaapi/exceptions.py
creaapi/graphenerpc.py
creaapi/node.py
creaapi/rpcutils.py
creaapi/version.py
creaapi/websocket.py
creabase/__init__.py
creabase/memo.py
creabase/objects.py
creabase/objecttypes.py
creabase/operationids.py
creabase/operations.py
creabase/signedtransactions.py
creabase/transactions.py
creabase/version.py
creagrapheneapi/__init__.py
creagraphenebase/__init__.py
creagraphenebase/account.py
creagraphenebase/base58.py
creagraphenebase/bip38.py
creagraphenebase/chains.py
creagraphenebase/dictionary.py
creagraphenebase/ecdsasig.py
creagraphenebase/objects.py
creagraphenebase/objecttypes.py
creagraphenebase/operationids.py
creagraphenebase/operations.py
creagraphenebase/py23.py
creagraphenebase/signedtransactions.py
creagraphenebase/types.py
creagraphenebase/version.py
crea-0.1.6.dist-info/LICENSE.txt
crea-0.1.6.dist-info/METADATA
crea-0.1.6.dist-info/WHEEL
crea-0.1.6.dist-info/entry_points.txt
crea-0.1.6.dist-info/top_level.txt
crea-0.1.6.dist-info/RECORD
