Metadata-Version: 2.1
Name: crea
Version: 0.1.6
Summary: Unofficial Python library for CREA
Home-page: https://github.com/creativechain/crea-python-lib
Author: Creativechain Foundation
Author-email: info@creativechain.org
License: UNKNOWN
Download-URL: https://github.com/creativechain/crea-python-lib/tarball/0.1.6
Keywords: crea,library,api,rpc
Platform: UNKNOWN
Classifier: License :: OSI Approved :: MIT License
Classifier: Operating System :: OS Independent
Classifier: Programming Language :: Python
Classifier: Programming Language :: Python :: 2.7
Classifier: Programming Language :: Python :: 3
Classifier: Programming Language :: Python :: 3.4
Classifier: Programming Language :: Python :: 3.5
Classifier: Programming Language :: Python :: 3.6
Classifier: Programming Language :: Python :: 3.7
Classifier: Development Status :: 4 - Beta
Classifier: Intended Audience :: Developers
Classifier: Intended Audience :: Financial and Insurance Industry
Classifier: Topic :: Office/Business :: Financial
Requires-Dist: future
Requires-Dist: ecdsa
Requires-Dist: requests
Requires-Dist: websocket-client
Requires-Dist: appdirs
Requires-Dist: Events
Requires-Dist: scrypt
Requires-Dist: pylibscrypt
Requires-Dist: pycryptodomex
Requires-Dist: pytz
Requires-Dist: Click
Requires-Dist: prettytable
Requires-Dist: pyyaml
